djangocms_zb_filer/__init__.py
djangocms_zb_filer/admin.py
djangocms_zb_filer/apps.py
djangocms_zb_filer/cms_plugins.py
djangocms_zb_filer/models.py
djangocms_zb_filer/tests.py
djangocms_zb_filer/urls.py
djangocms_zb_filer/views.py
djangocms_zb_filer/lib/__init__.py
djangocms_zb_filer/lib/choices.py
djangocms_zb_filer/lib/fields.py
djangocms_zb_filer/lib/forms.py
djangocms_zb_filer/lib/widgets.py
djangocms_zb_filer/lib/utils/__init__.py
djangocms_zb_filer/lib/utils/certificate_generator.py
djangocms_zb_filer/locale/es/LC_MESSAGES/django.mo
djangocms_zb_filer/locale/es/LC_MESSAGES/django.po
djangocms_zb_filer/migrations/0001_initial.py
djangocms_zb_filer/migrations/0002_auto_20220609_1443.py
djangocms_zb_filer/migrations/0003_auto_20221115_1512.py
djangocms_zb_filer/migrations/0004_publication_auto_send.py
djangocms_zb_filer/migrations/0005_auto_20240815_1447.py
djangocms_zb_filer/migrations/0006_auto_20240816_1300.py
djangocms_zb_filer/migrations/__init__.py
djangocms_zb_filer/tasks/__init__.py
djangocms_zb_filer/tasks/generate_send_certificate_auto.py
djangocms_zb_filer/templates/djangocms_zb_filer/default/certificate.html
djangocms_zb_filer/templates/djangocms_zb_filer/default/filer_list.html
djangocms_zb_filer/templates/djangocms_zb_filer/mail/send_certificate.txt
djangocms_zb_filer-1.1.2.dist-info/licenses/LICENSE
djangocms_zb_filer-1.1.2.dist-info/METADATA
djangocms_zb_filer-1.1.2.dist-info/WHEEL
djangocms_zb_filer-1.1.2.dist-info/top_level.txt
djangocms_zb_filer-1.1.2.dist-info/RECORD
